fileformats/extras/mrtrix3/__init__.py
fileformats/extras/mrtrix3/_version.py
fileformats/extras/mrtrix3/converters.py
fileformats/extras/mrtrix3/diffusion.py
fileformats/extras/mrtrix3/image.py
fileformats/extras/mrtrix3/tests/test_converters.py
fileformats_mrtrix3_extras-3.0.4.dist-info/METADATA
fileformats_mrtrix3_extras-3.0.4.dist-info/WHEEL
fileformats_mrtrix3_extras-3.0.4.dist-info/licenses/LICENSE
fileformats_mrtrix3_extras-3.0.4.dist-info/RECORD
